PiPilot/__init__.py
PiPilot/app.py
PiPilot/config.py
PiPilot/controller.py
PiPilot/default.conf
PiPilot/sbus.py
PiPilot/utils.py
PiPilot/webservice.py
PiPilot/websocket.py
PiPilot/ui/asset-manifest.json
PiPilot/ui/favicon.png
PiPilot/ui/index.html
PiPilot/ui/manifest.json
PiPilot/ui/service-worker.js
PiPilot/ui/static/css/main.1eebcbb7.css
PiPilot/ui/static/css/main.1eebcbb7.css.map
PiPilot/ui/static/js/main.fa8a49c2.js
PiPilot/ui/static/js/main.fa8a49c2.js.map
PiPilot/ui/static/media/glyphicons-halflings-regular.448c34a5.woff2
PiPilot/ui/static/media/glyphicons-halflings-regular.89889688.svg
PiPilot/ui/static/media/glyphicons-halflings-regular.e18bbf61.ttf
PiPilot/ui/static/media/glyphicons-halflings-regular.f4769f9b.eot
PiPilot/ui/static/media/glyphicons-halflings-regular.fa277232.woff
PiPilot-0.0.1.data/scripts/pipilot
PiPilot-0.0.1.dist-info/DESCRIPTION.rst
PiPilot-0.0.1.dist-info/METADATA
PiPilot-0.0.1.dist-info/RECORD
PiPilot-0.0.1.dist-info/WHEEL
PiPilot-0.0.1.dist-info/metadata.json
PiPilot-0.0.1.dist-info/top_level.txt
