Metadata-Version: 2.0
Name: PiPilot
Version: 0.0.1
Summary: A software aircraft controller for RaspberryPi
Home-page: https://github.com/ljanyst/pipilot
Author: Lukasz Janyst
Author-email: xyz@jany.st
License: GPL3 license
Platform: UNKNOWN
Classifier: Development Status :: 2 - Pre-Alpha
Classifier: License :: OSI Approved :: GNU General Public License v3 (GPLv3)
Classifier: Operating System :: Unix
Classifier: Topic :: Scientific/Engineering :: Human Machine Interfaces
Classifier: Intended Audience :: Developers
Classifier: Intended Audience :: Science/Research
Classifier: Operating System :: OS Independent
Classifier: Programming Language :: Python :: 3
Classifier: Programming Language :: Python :: 3.6
Classifier: Environment :: Console
Classifier: Environment :: No Input/Output (Daemon)
Classifier: Environment :: Web Environment
Requires-Dist: twisted
Requires-Dist: pyserial
Requires-Dist: autobahn
